{
  "Beg":        { "banner":"Connections", "type":"Sect", "icon":"fas fa-hourglass-start", "author":"Tom Flaherty", "date":"yyyy-mm-dd" },
  "Refine":     { "title":"Deliver",       "type":"Sect" },
  "Fulfuill":   { "title":"Deliver",       "type":"Sect" },
  "Enlight":    { "title":"Product",       "type":"Sect" },
  "Credits":    { "title":"Credits",      "type":"Cred", "icon":"fas fa-check-square" },
  "References": { "title":"References",   "type":"Refs", "icon":"fas fa-book-open"    },
  "Links":      { "title":"Links",        "type":"Link", "icon":"fas fa-link"         },
  "End":        { "banner":"The End",     "type":"Sect", "icon":"fas fa-stopwatch"    }
}